<?xml version="1.0" encoding="UTF-8"?>
<files psalm-version="4.4.1@9fd7a7d885b3a216cff8dec9d8c21a132f275224">
  <file src="src/CodeceptionAdapter.php">
    <MixedArgument occurrences="5">
      <code>$includedFiles</code>
      <code>$this-&gt;originalConfigContentParsed['bootstrap']</code>
      <code>$this-&gt;originalConfigContentParsed['bootstrap']</code>
      <code>$this-&gt;originalConfigContentParsed['coverage'] ?? []</code>
      <code>$this-&gt;originalConfigContentParsed['paths']['tests'] ?? 'tests'</code>
    </MixedArgument>
    <MixedAssignment occurrences="1">
      <code>$includedFiles</code>
    </MixedAssignment>
    <MixedInferredReturnType occurrences="1">
      <code>?string</code>
    </MixedInferredReturnType>
    <MixedReturnStatement occurrences="1">
      <code>$this-&gt;originalConfigContentParsed['bootstrap']</code>
    </MixedReturnStatement>
  </file>
  <file src="src/CodeceptionAdapterFactory.php">
    <MixedAssignment occurrences="1">
      <code>$codeceptionConfigContentParsed</code>
    </MixedAssignment>
    <MixedInferredReturnType occurrences="1">
      <code>array&lt;string, mixed&gt;</code>
    </MixedInferredReturnType>
    <MixedReturnStatement occurrences="1">
      <code>$codeceptionConfigContentParsed</code>
    </MixedReturnStatement>
    <MoreSpecificImplementedParamType occurrences="1">
      <code>$sourceDirectories</code>
    </MoreSpecificImplementedParamType>
  </file>
  <file src="src/CommandLineBuilder.php">
    <ForbiddenCode occurrences="1">
      <code>shell_exec('command -v php')</code>
    </ForbiddenCode>
    <UndefinedClass occurrences="1">
      <code>FinderException</code>
    </UndefinedClass>
  </file>
</files>
